[
  {
    "id": "planet_barren",
    "planet_type": "Barren",
    "resources": ["base_metals", "heavy_metals", "noble_metals"]
  },
  {
    "id": "planet_gas",
    "planet_type": "Gas",
    "resources": ["carbon_compounds", "ionic_solutions", "noble_gas", "reactive_gas", "suspended_plasma"]
  },
  {
    "id": "planet_ice",
    "planet_type": "Ice",
    "resources": ["noble_gas", "non_cs_crystals"]
  },
  {
    "id": "planet_lava",
    "planet_type": "Lava",
    "resources": ["base_metals", "felsic_magma", "heavy_metals"]
  },
  {
    "id": "planet_oceanic",
    "planet_type": "Oceanic",
    "resources": ["aqueous_liquids", "micro_organisms", "planktic_colonies"]
  },
  {
    "id": "planet_plasma",
    "planet_type": "Plasma",
    "resources": ["base_metals", "heavy_metals", "noble_metals", "non_cs_crystals", "suspended_plasma"]
  },
  {
    "id": "planet_storm",
    "planet_type": "Storm",
    "resources": ["ionic_solutions", "reactive_gas", "suspended_plasma"]
  },
  {
    "id": "planet_temperate",
    "planet_type": "Temperate",
    "resources": ["aqueous_liquids", "carbon_compounds", "complex_organisms", "micro_organisms", "autotrophs"]
  }
] 